pystime/__init__.py
pystime/cell_interface.py
pystime/read.py
pystime/spatial_graph.py
pystime/stime.py
pystime/version.py
pystime/data/SpaTalk_pathways.csv
pystime/data/__init__.py
pystime/data/stime-consensus_LRDB.csv
pystime-0.0.1.7.dist-info/METADATA
pystime-0.0.1.7.dist-info/WHEEL
pystime-0.0.1.7.dist-info/top_level.txt
pystime-0.0.1.7.dist-info/RECORD
